data/__init__.py
data/hfst.att
data/lexicon
franco_arabic_transliterator/__init__.py
franco_arabic_transliterator/franco_arabic_transliterator.py
tests/__init__.py
tests/test_basic_output.py
franco_arabic_transliterator-0.0.1.6.dist-info/LICENSE
franco_arabic_transliterator-0.0.1.6.dist-info/METADATA
franco_arabic_transliterator-0.0.1.6.dist-info/WHEEL
franco_arabic_transliterator-0.0.1.6.dist-info/top_level.txt
franco_arabic_transliterator-0.0.1.6.dist-info/RECORD
