Metadata-Version: 2.1
Name: franco-arabic-transliterator
Version: 0.0.1.6
Summary: Convert franco-arabic text into arabic
Home-page: https://github.com/AMR-KELEG/Franco-Arabic-Transliterator
Author: Amr Keleg
Author-email: amr_mohamed@live.com
License: GPLv3
License-File: LICENSE
Requires-Dist: hfst
